Metadata-Version: 2.1
Name: qusbt
Version: 1.1.0
Summary: Search-based testing of quantum programs
Home-page: https://github.com/Simula-COMPLEX/qusbt-tool
Author: Xinyi Wang
Author-email: xinyi@simula.no
Classifier: Programming Language :: Python :: 3
Classifier: License :: OSI Approved :: MIT License
Classifier: Operating System :: OS Independent
Requires-Python: >=3.8
License-File: LICENSE.py
Requires-Dist: qiskit ==1.2.1
Requires-Dist: qiskit-aer ==0.15.1
Requires-Dist: jmetalpy ==1.7.0
Requires-Dist: openpyxl
